pycep/.DS_Store
pycep/__init__.py
pycep/py.typed
pycep_cli-0.0.0.dist-info/entry_points.txt
pycep_cli-0.0.0.dist-info/LICENSE
pycep_cli-0.0.0.dist-info/WHEEL
pycep_cli-0.0.0.dist-info/METADATA
pycep_cli-0.0.0.dist-info/RECORD
